streamlit_image_gallery/__init__.py
streamlit_image_gallery/example.py
streamlit_image_gallery/frontend/build/asset-manifest.json
streamlit_image_gallery/frontend/build/bootstrap.min.css
streamlit_image_gallery/frontend/build/index.html
streamlit_image_gallery/frontend/build/static/js/main.26e13081.js
streamlit_image_gallery/frontend/build/static/js/main.26e13081.js.LICENSE.txt
streamlit_image_gallery/frontend/build/static/js/main.26e13081.js.map
streamlit_image_gallery_enhanced-1.0.1.dist-info/licenses/LICENSE
streamlit_image_gallery_enhanced-1.0.1.dist-info/METADATA
streamlit_image_gallery_enhanced-1.0.1.dist-info/WHEEL
streamlit_image_gallery_enhanced-1.0.1.dist-info/top_level.txt
streamlit_image_gallery_enhanced-1.0.1.dist-info/RECORD
